vertical_python-0.3.0.dist-info/METADATA
vertical_python-0.3.0.dist-info/WHEEL
vertical_python-0.3.0.dist-info/entry_points.txt
vertical_python/__init__.py
vertical_python/codec.py
vertical_python-0.3.0.dist-info/RECORD
