Metadata-Version: 2.1
Name: vertical-python
Version: 0.3.0
Summary: Python but vertical
Author-Email: sneakers-the-rat <sneakers-the-rat@protonmail.com>
License: MIT
Project-URL: homepage, https://github.com/sneakers-the-rat/vertical-python/
Project-URL: repository, https://github.com/sneakers-the-rat/vertical-python/
Requires-Python: >=3.10
Provides-Extra: tests
Requires-Dist: pytest>=9.0.1; extra == "tests"
